{
  "summary": {
    "currentCoverage": 47.38,
    "totalLines": 6428,
    "coveredLines": 3046,
    "uncoveredLines": 3382
  },
  "highImpactFiles": [
    {
      "path": "client/src/components/InteractiveTimeline.tsx",
      "lines": 517,
      "coverage": "23.79",
      "coverageGap": "76.21",
      "impactScore": 39401,
      "uncoveredLines": 394,
      "functions": "20.77",
      "branches": "21.95"
    },
    {
      "path": "client/src/pages/Reports.tsx",
      "lines": 412,
      "coverage": "36.89",
      "coverageGap": "63.11",
      "impactScore": 26001,
      "uncoveredLines": 260,
      "functions": "42.85",
      "branches": "39.60"
    },
    {
      "path": "src/server/api/controllers/ReportingController.ts",
      "lines": 259,
      "coverage": "0.77",
      "coverageGap": "99.23",
      "impactScore": 25701,
      "uncoveredLines": 257,
      "functions": "0.00",
      "branches": "0.00"
    },
    {
      "path": "client/src/components/modals/SmartAssignmentModal.tsx",
      "lines": 276,
      "coverage": "22.10",
      "coverageGap": "77.90",
      "impactScore": 21500,
      "uncoveredLines": 215,
      "functions": "19.75",
      "branches": "26.13"
    },
    {
      "path": "src/server/api/controllers/AssignmentsController.ts",
      "lines": 277,
      "coverage": "24.90",
      "coverageGap": "75.10",
      "impactScore": 20803,
      "uncoveredLines": 208,
      "functions": "34.14",
      "branches": "17.12"
    },
    {
      "path": "client/src/pages/PersonDetails.tsx",
      "lines": 276,
      "coverage": "29.34",
      "coverageGap": "70.66",
      "impactScore": 19502,
      "uncoveredLines": 195,
      "functions": "7.95",
      "branches": "1.88"
    },
    {
      "path": "src/server/api/controllers/ScenariosController.ts",
      "lines": 200,
      "coverage": "19.00",
      "coverageGap": "81.00",
      "impactScore": 16200,
      "uncoveredLines": 162,
      "functions": "40.00",
      "branches": "18.18"
    },
    {
      "path": "client/src/pages/Scenarios.tsx",
      "lines": 243,
      "coverage": "45.67",
      "coverageGap": "54.33",
      "impactScore": 13202,
      "uncoveredLines": 132,
      "functions": "26.96",
      "branches": "45.00"
    },
    {
      "path": "client/src/components/ProjectPhaseManager.tsx",
      "lines": 255,
      "coverage": "49.80",
      "coverageGap": "50.20",
      "impactScore": 12801,
      "uncoveredLines": 128,
      "functions": "43.37",
      "branches": "54.05"
    },
    {
      "path": "src/server/services/AssignmentRecalculationService.ts",
      "lines": 98,
      "coverage": "2.04",
      "coverageGap": "97.96",
      "impactScore": 9600,
      "uncoveredLines": 96,
      "functions": "4.54",
      "branches": "0.00"
    },
    {
      "path": "src/server/services/NotificationScheduler.ts",
      "lines": 94,
      "coverage": "9.57",
      "coverageGap": "90.43",
      "impactScore": 8500,
      "uncoveredLines": 85,
      "functions": "14.28",
      "branches": "0.00"
    },
    {
      "path": "src/server/services/ProjectPhaseCascadeService.ts",
      "lines": 172,
      "coverage": "52.32",
      "coverageGap": "47.68",
      "impactScore": 8201,
      "uncoveredLines": 82,
      "functions": "85.71",
      "branches": "38.04"
    },
    {
      "path": "client/src/components/modals/PersonModal.tsx",
      "lines": 101,
      "coverage": "38.61",
      "coverageGap": "61.39",
      "impactScore": 6200,
      "uncoveredLines": 62,
      "functions": "18.42",
      "branches": "18.86"
    },
    {
      "path": "client/src/utils/date.ts",
      "lines": 88,
      "coverage": "29.54",
      "coverageGap": "70.46",
      "impactScore": 6200,
      "uncoveredLines": 62,
      "functions": "4.54",
      "branches": "0.00"
    },
    {
      "path": "client/src/pages/ProjectTypeDetails.tsx",
      "lines": 135,
      "coverage": "54.81",
      "coverageGap": "45.19",
      "impactScore": 6101,
      "uncoveredLines": 61,
      "functions": "31.25",
      "branches": "45.22"
    }
  ],
  "top7Analysis": {
    "files": [
      "client/src/components/InteractiveTimeline.tsx",
      "client/src/pages/Reports.tsx",
      "src/server/api/controllers/ReportingController.ts",
      "client/src/components/modals/SmartAssignmentModal.tsx",
      "src/server/api/controllers/AssignmentsController.ts",
      "client/src/pages/PersonDetails.tsx",
      "src/server/api/controllers/ScenariosController.ts"
    ],
    "totalImpactScore": 169108,
    "totalUncoveredLines": 1691,
    "potentialCoverageGain": 26.31,
    "projectedCoverage": 73.69
  }
}